{
  "Name": "Adder",
  "Colour": "#B87005",
  "InputPins": [
    {
      "Name": "Pin",
      "ID": 2035347471,
      "PositionY": 1.08333349,
      "ColourThemeName": "Red"
    },
    {
      "Name": "Pin",
      "ID": 168793561,
      "PositionY": 0.481481552,
      "ColourThemeName": "Red"
    },
    {
      "Name": "Pin",
      "ID": 298526241,
      "PositionY": -0.1666668,
      "ColourThemeName": "Red"
    }
  ],
  "OutputPins": [
    {
      "Name": "Pin",
      "ID": 2082877053,
      "PositionY": 1.02777779,
      "ColourThemeName": "Red"
    },
    {
      "Name": "Pin",
      "ID": 1200917505,
      "PositionY": 0.0370371342,
      "ColourThemeName": "Red"
    }
  ],
  "SubChips": [
    {
      "Name": "AND",
      "ID": 236404638,
      "Points": [
        {
          "X": -5.638889,
          "Y": 1.69444442
        }
      ],
      "Data": null
    },
    {
      "Name": "XOR",
      "ID": 814156172,
      "Points": [
        {
          "X": -4.333333,
          "Y": 0.9722221
        }
      ],
      "Data": null
    },
    {
      "Name": "XOR",
      "ID": 55963633,
      "Points": [
        {
          "X": 0.0277773552,
          "Y": 1.52777791
        }
      ],
      "Data": null
    },
    {
      "Name": "OR",
      "ID": 1104030352,
      "Points": [
        {
          "X": 2.44444418,
          "Y": 0.02777791
        }
      ],
      "Data": null
    },
    {
      "Name": "AND",
      "ID": 386196518,
      "Points": [
        {
          "X": -1.62037063,
          "Y": 0.6944442
        }
      ],
      "Data": null
    }
  ],
  "Connections": [
    {
      "Source": {
        "PinType": 1,
        "SubChipID": 0,
        "PinID": 2035347471
      },
      "Target": {
        "PinType": 3,
        "SubChipID": 236404638,
        "PinID": 0
      },
      "WirePoints": [
        {
          "X": -7.837778,
          "Y": 1.08333349
        },
        {
          "X": -7.82407427,
          "Y": 1.83333337
        },
        {
          "X": -6.188889,
          "Y": 1.81444442
        }
      ],
      "ColourThemeName": "Red"
    },
    {
      "Source": {
        "PinType": 1,
        "SubChipID": 0,
        "PinID": 168793561
      },
      "Target": {
        "PinType": 3,
        "SubChipID": 236404638,
        "PinID": 1
      },
      "WirePoints": [
        {
          "X": -7.837778,
          "Y": 0.481481552
        },
        {
          "X": -6.47222233,
          "Y": 0.490740538
        },
        {
          "X": -6.48148155,
          "Y": 1.574074
        },
        {
          "X": -6.188889,
          "Y": 1.57444441
        }
      ],
      "ColourThemeName": "Red"
    },
    {
      "Source": {
        "PinType": 1,
        "SubChipID": 0,
        "PinID": 2035347471
      },
      "Target": {
        "PinType": 3,
        "SubChipID": 814156172,
        "PinID": 2110307452
      },
      "WirePoints": [
        {
          "X": -7.837778,
          "Y": 1.08333349
        },
        {
          "X": -4.883333,
          "Y": 1.09222209
        }
      ],
      "ColourThemeName": "Red"
    },
    {
      "Source": {
        "PinType": 1,
        "SubChipID": 0,
        "PinID": 168793561
      },
      "Target": {
        "PinType": 3,
        "SubChipID": 814156172,
        "PinID": 608470121
      },
      "WirePoints": [
        {
          "X": -7.837778,
          "Y": 0.481481552
        },
        {
          "X": -5.148148,
          "Y": 0.537037253
        },
        {
          "X": -5.148148,
          "Y": 0.8518517
        },
        {
          "X": -4.883333,
          "Y": 0.8522221
        }
      ],
      "ColourThemeName": "Red"
    },
    {
      "Source": {
        "PinType": 4,
        "SubChipID": 55963633,
        "PinID": 829496259
      },
      "Target": {
        "PinType": 2,
        "SubChipID": 0,
        "PinID": 2082877053
      },
      "WirePoints": [
        {
          "X": 0.5777774,
          "Y": 1.52777791
        },
        {
          "X": 1.26851833,
          "Y": 1.51851833
        },
        {
          "X": 1.24084783,
          "Y": 0.9962406
        },
        {
          "X": 7.837778,
          "Y": 1.02777779
        }
      ],
      "ColourThemeName": "Red"
    },
    {
      "Source": {
        "PinType": 4,
        "SubChipID": 814156172,
        "PinID": 829496259
      },
      "Target": {
        "PinType": 3,
        "SubChipID": 55963633,
        "PinID": 2110307452
      },
      "WirePoints": [
        {
          "X": -3.783333,
          "Y": 0.9722221
        },
        {
          "X": -2.87962985,
          "Y": 0.9537035
        },
        {
          "X": -2.87962985,
          "Y": 1.63888872
        },
        {
          "X": -0.522222638,
          "Y": 1.64777792
        }
      ],
      "ColourThemeName": "Red"
    },
    {
      "Source": {
        "PinType": 1,
        "SubChipID": 0,
        "PinID": 298526241
      },
      "Target": {
        "PinType": 3,
        "SubChipID": 55963633,
        "PinID": 608470121
      },
      "WirePoints": [
        {
          "X": -7.837778,
          "Y": -0.1666668
        },
        {
          "X": -0.8518521,
          "Y": -0.0833332539
        },
        {
          "X": -0.8425925,
          "Y": 1.34259284
        },
        {
          "X": -0.522222638,
          "Y": 1.40777791
        }
      ],
      "ColourThemeName": "Red"
    },
    {
      "Source": {
        "PinType": 4,
        "SubChipID": 1104030352,
        "PinID": 766529950
      },
      "Target": {
        "PinType": 2,
        "SubChipID": 0,
        "PinID": 1200917505
      },
      "WirePoints": [
        {
          "X": 2.89444423,
          "Y": 0.02777791
        },
        {
          "X": 7.837778,
          "Y": 0.0370371342
        }
      ],
      "ColourThemeName": "Red"
    },
    {
      "Source": {
        "PinType": 4,
        "SubChipID": 814156172,
        "PinID": 829496259
      },
      "Target": {
        "PinType": 3,
        "SubChipID": 386196518,
        "PinID": 0
      },
      "WirePoints": [
        {
          "X": -3.783333,
          "Y": 0.9722221
        },
        {
          "X": -3.06481481,
          "Y": 0.990740657
        },
        {
          "X": -3.027778,
          "Y": 0.814814568
        },
        {
          "X": -2.17037058,
          "Y": 0.8144442
        }
      ],
      "ColourThemeName": "Red"
    },
    {
      "Source": {
        "PinType": 4,
        "SubChipID": 386196518,
        "PinID": 2
      },
      "Target": {
        "PinType": 3,
        "SubChipID": 1104030352,
        "PinID": 850555830
      },
      "WirePoints": [
        {
          "X": -1.07037067,
          "Y": 0.6944442
        },
        {
          "X": 1.97222185,
          "Y": 0.6203705
        },
        {
          "X": 1.97218418,
          "Y": 0.174546614
        },
        {
          "X": 1.99444413,
          "Y": 0.147777915
        }
      ],
      "ColourThemeName": "Red"
    },
    {
      "Source": {
        "PinType": 1,
        "SubChipID": 0,
        "PinID": 298526241
      },
      "Target": {
        "PinType": 3,
        "SubChipID": 386196518,
        "PinID": 1
      },
      "WirePoints": [
        {
          "X": -7.837778,
          "Y": -0.1666668
        },
        {
          "X": -2.4533658,
          "Y": -0.102437355
        },
        {
          "X": -2.44444442,
          "Y": 0.6111109
        },
        {
          "X": -2.17037058,
          "Y": 0.5744442
        }
      ],
      "ColourThemeName": "Red"
    },
    {
      "Source": {
        "PinType": 4,
        "SubChipID": 236404638,
        "PinID": 2
      },
      "Target": {
        "PinType": 3,
        "SubChipID": 1104030352,
        "PinID": 2016941494
      },
      "WirePoints": [
        {
          "X": -5.08888865,
          "Y": 1.69444442
        },
        {
          "X": -1.064815,
          "Y": 1.79629624
        },
        {
          "X": -1.05606461,
          "Y": -0.112359121
        },
        {
          "X": 1.99444413,
          "Y": -0.09222209
        }
      ],
      "ColourThemeName": "Red"
    }
  ]
}